odoo10_addon_sale_operating_unit-10.0.1.1.0-py2.7-nspkg.pth
odoo/addons/sale_operating_unit/README.rst
odoo/addons/sale_operating_unit/__init__.py
odoo/addons/sale_operating_unit/__manifest__.py
odoo/addons/sale_operating_unit/models/__init__.py
odoo/addons/sale_operating_unit/models/crm_team.py
odoo/addons/sale_operating_unit/models/sale.py
odoo/addons/sale_operating_unit/report/__init__.py
odoo/addons/sale_operating_unit/report/sale_report.py
odoo/addons/sale_operating_unit/security/sale_security.xml
odoo/addons/sale_operating_unit/tests/__init__.py
odoo/addons/sale_operating_unit/tests/test_sale_operating_unit.py
odoo/addons/sale_operating_unit/views/sale_report_view.xml
odoo/addons/sale_operating_unit/views/sale_view.xml
odoo10_addon_sale_operating_unit-10.0.1.1.0.dist-info/DESCRIPTION.rst
odoo10_addon_sale_operating_unit-10.0.1.1.0.dist-info/METADATA
odoo10_addon_sale_operating_unit-10.0.1.1.0.dist-info/RECORD
odoo10_addon_sale_operating_unit-10.0.1.1.0.dist-info/WHEEL
odoo10_addon_sale_operating_unit-10.0.1.1.0.dist-info/metadata.json
odoo10_addon_sale_operating_unit-10.0.1.1.0.dist-info/namespace_packages.txt
odoo10_addon_sale_operating_unit-10.0.1.1.0.dist-info/top_level.txt
